tripio_hundo-0.0.1.dist-info/licenses/LICENSE
tripio_hundo1018/__init__.py
tripio_hundo1018/command.py
tripio_hundo1018/event.py
tripio_hundo1018/future.py
tripio_hundo1018/response.py
tripio_hundo1018/result.py
tripio_hundo-0.0.1.dist-info/METADATA
tripio_hundo-0.0.1.dist-info/WHEEL
tripio_hundo-0.0.1.dist-info/top_level.txt
tripio_hundo-0.0.1.dist-info/RECORD
